wallapy/__init__.py
wallapy/check.py
wallapy/config.py
wallapy/exceptions.py
wallapy/fetch_api.py
wallapy/logutils.py
wallapy/request_handler.py
wallapy/utils.py
wallapy-0.6.6.dist-info/LICENSE
wallapy-0.6.6.dist-info/METADATA
wallapy-0.6.6.dist-info/WHEEL
wallapy-0.6.6.dist-info/RECORD
