Metadata-Version: 2.3
Name: wallapy
Version: 0.6.6
Summary: A Python tool to search Wallapop items
License: Apache-2.0
Author: Duccioo
Author-email: meconcelliduccio@hotmail.it
Requires-Python: >=3.12
Classifier: License :: OSI Approved :: Apache Software License
Classifier: Programming Language :: Python :: 3
Classifier: Programming Language :: Python :: 3.12
Classifier: Programming Language :: Python :: 3.13
Requires-Dist: beautifulsoup4 (>=4.13.4,<5.0.0)
Requires-Dist: httpx (>=0.28.1,<0.29.0)
Requires-Dist: levenshtein (>=0.27.1,<0.28.0)
Requires-Dist: lxml (>=5.3.2,<6.0.0)
Requires-Dist: pytz (>=2025.2,<2026.0)
Requires-Dist: requests (>=2.32.3,<3.0.0)
Project-URL: Repository, https://github.com/duccioo/WallaPy
